promptmanager/__init__.py
promptmanager/db.sql
promptmanager/manage.py
promptmanager/requirements.txt
promptmanager/PromptManager/__init__.py
promptmanager/PromptManager/asgi.py
promptmanager/PromptManager/urls.py
promptmanager/PromptManager/view.py
promptmanager/PromptManager/wsgi.py
promptmanager/PromptManager/settings/__init__.py
promptmanager/PromptManager/settings/base.py
promptmanager/PromptManager/settings/dev.py
promptmanager/PromptManager/settings/install.py
promptmanager/PromptManager/settings/prod.py
promptmanager/PromptManager/settings/prod_test.py
promptmanager/app_app/__init__.py
promptmanager/app_app/admin.py
promptmanager/app_app/apps.py
promptmanager/app_app/models.py
promptmanager/app_app/sdk_example.md
promptmanager/app_app/tests.py
promptmanager/app_app/urls.py
promptmanager/app_app/views.py
promptmanager/app_app/migrations/__init__.py
promptmanager/app_chat/__init__.py
promptmanager/app_chat/admin.py
promptmanager/app_chat/apps.py
promptmanager/app_chat/models.py
promptmanager/app_chat/tests.py
promptmanager/app_chat/urls.py
promptmanager/app_chat/views.py
promptmanager/app_chat/migrations/__init__.py
promptmanager/app_common/__init__.py
promptmanager/app_common/category_type_default.py
promptmanager/app_common/collect_status_type.py
promptmanager/app_common/constant.py
promptmanager/app_common/database_util.py
promptmanager/app_common/enum_module_path.py
promptmanager/app_common/enum_publish_type.py
promptmanager/app_common/enum_source_type.py
promptmanager/app_common/file_util.py
promptmanager/app_common/http_request_util.py
promptmanager/app_common/json_util.py
promptmanager/app_common/page_util.py
promptmanager/app_common/result_maker.py
promptmanager/app_flow/__init__.py
promptmanager/app_flow/admin.py
promptmanager/app_flow/apps.py
promptmanager/app_flow/models.py
promptmanager/app_flow/tests.py
promptmanager/app_flow/urls.py
promptmanager/app_flow/views.py
promptmanager/app_flow/migrations/__init__.py
promptmanager/app_model/__init__.py
PromptManager-1.0.1.dist-info/METADATA
PromptManager-1.0.1.dist-info/WHEEL
PromptManager-1.0.1.dist-info/entry_points.txt
PromptManager-1.0.1.dist-info/top_level.txt
PromptManager-1.0.1.dist-info/RECORD
