Metadata-Version: 2.1
Name: PromptManager
Version: 1.0.1
Home-page: 
Author: aps
Author-email: aps@zetyun.com
Classifier: Programming Language :: Python :: 3.9
Classifier: License :: OSI Approved :: Apache Software License
Requires-Python: >=3.9
Requires-Dist: asgiref (==3.7.2)
Requires-Dist: Django (==4.2.4)
Requires-Dist: pip (==23.2.1)
Requires-Dist: pytz (==2023.3)
Requires-Dist: setuptools (==68.0.0)
Requires-Dist: sqlparse (==0.4.4)
Requires-Dist: typing-extensions (==4.7.1)
Requires-Dist: tzdata (==2023.3)
Requires-Dist: wheel (==0.38.4)
Requires-Dist: Requests (==2.31.0)
Requires-Dist: pandas (==2.1.0)
Requires-Dist: python-docx (==0.8.11)
Requires-Dist: openpyxl (==3.1.2)
Requires-Dist: xlrd (==2.0.1)
Requires-Dist: psutil (==5.9.0)
Requires-Dist: numpy (==1.26.0)
Requires-Dist: tenacity (==8.2.2)
